{
  "kind": "collectionType",
  "collectionName": "orders",
  "info": {
    "singularName": "order",
    "pluralName": "orders",
    "displayName": "Order",
    "description": ""
  },
  "options": {
    "draftAndPublish": true
  },
  "pluginOptions": {},
  "attributes": {
    "city": {
      "type": "string",
      "required": true
    },
    "state": {
      "type": "string",
      "required": true
    },
    "pin": {
      "type": "integer"
    },
    "ShippingAddress": {
      "type": "richtext",
      "required": true
    },
    "items": {
      "type": "json",
      "required": true
    },
    "amount": {
      "type": "integer",
      "required": true
    },
    "user": {
      "type": "string",
      "required": true
    }
  }
}
